cvtease/__init__.py
cvtease/cli.py
cvtease/game.py
cvtease/gui.py
cvtease/recoface.py
cvtease/asset/__init__.py
cvtease/data/__init__.py
cvtease/function/__init__.py
cvtease/function/eyeAft.py
cvtease/style/__init__.py
cvtease/style/style.py
cvtease-0.1.18.dist-info/LICENSE
cvtease-0.1.18.dist-info/METADATA
cvtease-0.1.18.dist-info/WHEEL
cvtease-0.1.18.dist-info/entry_points.txt
cvtease-0.1.18.dist-info/top_level.txt
cvtease-0.1.18.dist-info/RECORD
