Metadata-Version: 2.1
Name: cvtease
Version: 0.1.18
Summary: A CLI tool for computer vision that is under development. Includes a space shooter game using ASCII art.
Home-page: https://github.com/w3cdpass/cvtease
Author: w3cdpass
Author-email: w3cdpass <kupasva663@gmail.com>
License: Copyright (c) 2018 The Python Packaging Authority
Project-URL: Homepage, https://github.com/w3cdpass/cvtease
Project-URL: Bug Tracker, https://github.com/w3cdpass/cvtease/issues
Classifier: Development Status :: 3 - Alpha
Classifier: Intended Audience :: Developers
Classifier: Programming Language :: Python :: 3
Classifier: Programming Language :: Python :: 3.7
Classifier: Programming Language :: Python :: 3.8
Classifier: Programming Language :: Python :: 3.9
Classifier: Programming Language :: Python :: 3.10
Classifier: Programming Language :: Python :: 3.11
Requires-Python: >=3.7
License-File: LICENSE
Requires-Dist: click
Requires-Dist: colorama
Requires-Dist: opencv-python
